tree_sitter_lexc/__init__.pyi
tree_sitter_lexc/_binding.abi3.so
tree_sitter_lexc/py.typed
tree_sitter_lexc/binding.c
tree_sitter_lexc/__init__.py
tree_sitter_lexc/queries/highlights.scm
tree_sitter_lexc-1.0.0.dist-info/RECORD
tree_sitter_lexc-1.0.0.dist-info/top_level.txt
tree_sitter_lexc-1.0.0.dist-info/METADATA
tree_sitter_lexc-1.0.0.dist-info/WHEEL
