Metadata-Version: 2.1
Name: tree-sitter-lexc
Version: 1.0.0
Summary: tree-sitter grammar for hfst-lexc
Author: Daniel Swanson
License: GPL-3.0-or-later
Project-URL: Homepage, https://github.com/apertium/tree-sitter-apertium
Keywords: incremental,parsing,tree-sitter,lexc
Classifier: Intended Audience :: Developers
Classifier: Topic :: Software Development :: Compilers
Classifier: Topic :: Text Processing :: Linguistic
Classifier: Typing :: Typed
Requires-Python: >=3.9
Provides-Extra: core
Requires-Dist: tree-sitter ~=0.22 ; extra == 'core'
